razor_engine/__init__.py
razor_engine-0.0.1.dist-info/METADATA
razor_engine-0.0.1.dist-info/WHEEL
razor_engine-0.0.1.dist-info/top_level.txt
razor_engine-0.0.1.dist-info/RECORD
