Metadata-Version: 2.1
Name: razor-engine
Version: 0.0.1
Summary: Razor Dev Tools for Razorthink AI
Home-page: https://razorthink.com
Author: Razorthink
Author-email: sandeep.kumar@razorthink.com
License: UNKNOWN
Platform: UNKNOWN
Requires-Python: >=3.7
